passageidentity/__init__.py
passageidentity/auth.py
passageidentity/errors.py
passageidentity/passage.py
passageidentity/user.py
passageidentity/models/__init__.py
passageidentity/models/magic_link_args.py
passageidentity/models/magic_link_options.py
passageidentity/openapi_client/__init__.py
passageidentity/openapi_client/api_client.py
passageidentity/openapi_client/api_response.py
passageidentity/openapi_client/configuration.py
passageidentity/openapi_client/exceptions.py
passageidentity/openapi_client/py.typed
passageidentity/openapi_client/rest.py
passageidentity/openapi_client/api/__init__.py
passageidentity/openapi_client/api/magic_links_api.py
passageidentity/openapi_client/api/tokens_api.py
passageidentity/openapi_client/api/user_devices_api.py
passageidentity/openapi_client/api/users_api.py
passageidentity/openapi_client/models/__init__.py
passageidentity/openapi_client/models/apple_user_social_connection.py
passageidentity/openapi_client/models/create_magic_link_request.py
passageidentity/openapi_client/models/create_user_args.py
passageidentity/openapi_client/models/github_user_social_connection.py
passageidentity/openapi_client/models/google_user_social_connection.py
passageidentity/openapi_client/models/link.py
passageidentity/openapi_client/models/list_devices_response.py
passageidentity/openapi_client/models/list_paginated_users_item.py
passageidentity/openapi_client/models/list_paginated_users_response.py
passageidentity/openapi_client/models/magic_link.py
passageidentity/openapi_client/models/magic_link_channel.py
passageidentity/openapi_client/models/magic_link_language.py
passageidentity/openapi_client/models/magic_link_response.py
passageidentity/openapi_client/models/magic_link_type.py
passageidentity/openapi_client/models/model400_error.py
passageidentity/openapi_client/models/model401_error.py
passageidentity/openapi_client/models/model403_error.py
passageidentity/openapi_client/models/model404_error.py
passage_identity-3.0.2.dist-info/LICENSE
passage_identity-3.0.2.dist-info/METADATA
passage_identity-3.0.2.dist-info/WHEEL
passage_identity-3.0.2.dist-info/top_level.txt
passage_identity-3.0.2.dist-info/RECORD
