Metadata-Version: 2.1
Name: passage-identity
Version: 3.0.2
Summary: Passkey Complete for Python - Integrate into your Python API or service to enable a completely passwordless standalone auth solution with Passage by 1Password
Author-email: Passage by 1Password <support@passage.id>
License: MIT License
Project-URL: Documentation, https://docs.passage.id/complete
Project-URL: Bug Tracker, https://github.com/passageidentity/.github/blob/main/SUPPORT.md
Classifier: Development Status :: 5 - Production/Stable
Classifier: Intended Audience :: Developers
Classifier: License :: OSI Approved :: MIT License
Classifier: Operating System :: OS Independent
Classifier: Topic :: Security
Classifier: Programming Language :: Python
Classifier: Programming Language :: Python :: 3
Classifier: Programming Language :: Python :: 3 :: Only
Classifier: Programming Language :: Python :: 3.8
Classifier: Programming Language :: Python :: 3.9
Classifier: Programming Language :: Python :: 3.10
Classifier: Programming Language :: Python :: 3.11
Classifier: Programming Language :: Python :: 3.12
Classifier: Programming Language :: Python :: 3.13
Requires-Python: >=3.8
License-File: LICENSE
Requires-Dist: cryptography ~=44.0
Requires-Dist: pydantic ~=2.10
Requires-Dist: pyjwt ~=2.9
Requires-Dist: python-dateutil ~=2.9
Requires-Dist: requests ~=2.32
Provides-Extra: dev
Requires-Dist: passage-identity[lint,test] ; extra == 'dev'
Provides-Extra: lint
Requires-Dist: ruff ~=0.8 ; extra == 'lint'
Provides-Extra: test
Requires-Dist: pytest ~=8.3 ; extra == 'test'
